{"templateId":"a0d9b8c7-d29b-4ebb-97ce-76868b0688fe","name":"otrs.create/update","description":"Create/update a config item. The fields object_title, cmdb_status_title, manufactuere_title are used for the import. Config items are filtered according to the object-type “client”. All objects are created in the otrs standard class “Hardware”. The identifier field is a config item name.","connection":{"title":"cre","description":"","fromConnector":{"connectorId":27,"invoker":{"name":"i-doit","links":[]},"methods":[{"nodeId":null,"index":"0","name":"cmdb.objects.read","color":"#FFCFB5","request":{"nodeId":null,"endpoint":"{url}","method":"POST","header":null,"body":{"method":"cmdb.objects.read","id":"1","params":{"filter":{"sys_id":"","firstname":"","ids":[],"type_title":"","type":["10"],"title":"","email":"","lastname":""},"apikey":"{apikey}","limit":"","order_by":"","language":"","sort":""},"version":"2.0"},"links":[]},"response":{"nodeId":null,"name":"response","success":{"nodeId":null,"status":"200","header":null,"body":{"result":[{"cmdb_status_title":"","image":"","sysid":"","created":"","type_title":"","cmdb_status":"","id":"","title":"","type":"","updated":"","status":"","type_group_title":""}],"id":"","jsonrpc":""},"links":[]},"fail":{"nodeId":null,"status":"200","header":null,"body":{"error":{"code":"","data":"","message":""}},"links":[]},"links":[]},"links":[]},{"nodeId":null,"index":"1_0","name":"cmdb.category.read","color":"#C77E7E","request":{"nodeId":null,"endpoint":"{url}","method":"POST","header":null,"body":{"method":"cmdb.category.read","id":"1","params":{"apikey":"{apikey}","objID":"#FFCFB5.(response).success.result[].id","language":"","category":"C__CATG__MODEL"},"version":"2.0"},"links":[]},"response":{"nodeId":null,"name":"response","success":{"nodeId":null,"status":"200","header":null,"body":{"result":[{"hostname":"","objID":"","id":""}]},"links":[]},"fail":{"nodeId":null,"status":"200","header":null,"body":{"error":{"code":"","data":"","message":""}},"links":[]},"links":[]},"links":[]}],"operators":[{"nodeId":null,"type":"loop","index":"1","condition":{"relationalOperator":"","leftStatement":{"color":"#FFCFB5","field":"success.result[]","type":"response","rightPropertyValue":"","links":[]},"rightStatement":null,"links":[]},"links":[]}],"links":[]},"toConnector":{"connectorId":28,"invoker":{"name":"otrs","links":[]},"methods":[{"nodeId":null,"index":"0","name":"ConfigItemSearch","color":"#6477AB","request":{"nodeId":null,"endpoint":"{url}/{WebService}/ConfigItemSearch/{UserLogin}/{Password}","method":"POST","header":null,"body":{"ConfigItem":{"InciState":"","Number":"","DeplState":"","Class":"Hardware","Name":""}},"links":[]},"response":{"nodeId":null,"name":"response","success":{"nodeId":null,"status":"200","header":null,"body":{"ConfigItemIDs":[]},"links":[]},"fail":{"nodeId":null,"status":"200","header":null,"body":{"Error":{"ErrorCode":"","ErrorMessage":""}},"links":[]},"links":[]},"links":[]},{"nodeId":null,"index":"1_0","name":"ConfigItemGet","color":"#98BEC7","request":{"nodeId":null,"endpoint":"{url}/{WebService}/ConfigItemGet/{UserLogin}/{Password}","method":"POST","header":null,"body":{"ConfigItemID":"#6477AB.(response).success.ConfigItemIDs[]"},"links":[]},"response":{"nodeId":null,"name":"response","success":{"nodeId":null,"status":"200","header":null,"body":{"ConfigItem":[{"InciState":"","Number":"","DeplState":"","Class":"","CIXMLData":{"Vendor":""},"Name":""}]},"links":[]},"fail":{"nodeId":null,"status":"500","header":null,"body":{"faultcode":"","faultstring":""},"links":[]},"links":[]},"links":[]},{"nodeId":null,"index":"1_1_0_0","name":"ConfigItemCreate","color":"#9EC798","request":{"nodeId":null,"endpoint":"{url}/{WebService}/ConfigItemCreate/{UserLogin}/{Password}","method":"POST","header":null,"body":{"ConfigItem":{"InciState":"#FFCFB5.(response).success.result[].cmdb_status_title","DeplState":"Production","Class":"Hardware","CIXMLData":{"Vendor":"#C77E7E.(response).success.result[]"},"Name":"#FFCFB5.(response).success.result[].title"}},"links":[]},"response":{"nodeId":null,"name":"response","success":{"nodeId":null,"status":"200","header":null,"body":{"Number":"","ConfigItemID":""},"links":[]},"fail":{"nodeId":null,"status":"500","header":null,"body":{"faultstring":"","faultcode":""},"links":[]},"links":[]},"links":[]},{"nodeId":null,"index":"1_1_1_0","name":"ConfigItemUpdate","color":"#E6E6EA","request":{"nodeId":null,"endpoint":"{url}/{WebService}/ConfigItemUpdate/{UserLogin}/{Password}","method":"POST","header":null,"body":{"ConfigItem":{"InciState":"#FFCFB5.(response).success.result[].cmdb_status_title","DeplState":"Production","Class":"Hardware","CIXMLData":{"Vendor":""},"Name":"#FFCFB5.(response).success.result[].title"},"ConfigItemID":"#FFCFB5.(response).success.result[].title;#98BEC7.(response).success.ConfigItem[]"},"links":[]},"response":{"nodeId":null,"name":"response","success":{"nodeId":null,"status":"200","header":null,"body":{"Number":"","ConfigItemID":""},"links":[]},"fail":{"nodeId":null,"status":"500","header":null,"body":{"faultcode":"","faultstring":""},"links":[]},"links":[]},"links":[]},{"nodeId":null,"index":"2_0_0","name":"ConfigItemCreate","color":"#BFC798","request":{"nodeId":null,"endpoint":"{url}/{WebService}/ConfigItemCreate/{UserLogin}/{Password}","method":"POST","header":null,"body":{"ConfigItem":{"InciState":"#FFCFB5.(response).success.result[].cmdb_status_title","DeplState":"Production","Class":"Hardware","CIXMLData":{"Vendor":"#C77E7E.(response).success.result[]"},"Name":"#FFCFB5.(response).success.result[].title"}},"links":[]},"response":{"nodeId":null,"name":"response","success":{"nodeId":null,"status":"200","header":null,"body":{"Number":"","ConfigItemID":""},"links":[]},"fail":{"nodeId":null,"status":"500","header":null,"body":{"faultstring":"","faultcode":""},"links":[]},"links":[]},"links":[]}],"operators":[{"nodeId":null,"type":"if","index":"1","condition":{"relationalOperator":"NotEmpty","leftStatement":{"color":"#6477AB","field":"success.ConfigItemIDs[]","type":"response","rightPropertyValue":"","links":[]},"rightStatement":null,"links":[]},"links":[]},{"nodeId":null,"type":"loop","index":"1_1","condition":{"relationalOperator":"","leftStatement":{"color":"#FFCFB5","field":"success.result[]","type":"response","rightPropertyValue":"","links":[]},"rightStatement":null,"links":[]},"links":[]},{"nodeId":null,"type":"if","index":"1_1_0","condition":{"relationalOperator":"NotContains","leftStatement":{"color":"#98BEC7","field":"success.ConfigItem[]","type":"response","rightPropertyValue":"","links":[]},"rightStatement":{"color":"#FFCFB5","field":"success.result[].title","type":"response","rightPropertyValue":"Name","links":[]},"links":[]},"links":[]},{"nodeId":null,"type":"if","index":"1_1_1","condition":{"relationalOperator":"Contains","leftStatement":{"color":"#98BEC7","field":"success.ConfigItem[]","type":"response","rightPropertyValue":"","links":[]},"rightStatement":{"color":"#FFCFB5","field":"success.result[].title","type":"response","rightPropertyValue":"Name","links":[]},"links":[]},"links":[]},{"nodeId":null,"type":"if","index":"2","condition":{"relationalOperator":"IsEmpty","leftStatement":{"color":"#6477AB","field":"success.ConfigItemIDs[]","type":"response","rightPropertyValue":"","links":[]},"rightStatement":null,"links":[]},"links":[]},{"nodeId":null,"type":"loop","index":"2_0","condition":{"relationalOperator":"","leftStatement":{"color":"#FFCFB5","field":"success.result[]","type":"response","rightPropertyValue":"","links":[]},"rightStatement":null,"links":[]},"links":[]}],"links":[]},"fieldBinding":[{"from":[{"color":"#6477AB","type":"response","field":"success.ConfigItemIDs[]","links":[]}],"enhancement":{"enhanceId":null,"name":"","description":"","expertCode":"RESULT_VAR = VAR_0;","expertVar":"//var RESULT_VAR = #98BEC7.(request).ConfigItemID[];\n//var VAR_0 = #6477AB.(response).success.ConfigItemIDs[];","simpleCode":null,"language":"js","links":[]},"to":[{"color":"#98BEC7","type":"request","field":"ConfigItemID[]","links":[]}],"links":[]},{"from":[{"color":"#FFCFB5","type":"response","field":"success.result[].title","links":[]}],"enhancement":{"enhanceId":null,"name":"","description":"","expertCode":"RESULT_VAR = VAR_0;","expertVar":"//var RESULT_VAR = #9EC798.(request).ConfigItem.Name;\n//var VAR_0 = #FFCFB5.(response).success.result[].title;","simpleCode":null,"language":"js","links":[]},"to":[{"color":"#9EC798","type":"request","field":"ConfigItem.Name","links":[]}],"links":[]},{"from":[{"color":"#FFCFB5","type":"response","field":"success.result[].title","links":[]}],"enhancement":{"enhanceId":null,"name":"","description":"","expertCode":"RESULT_VAR = VAR_0;","expertVar":"//var RESULT_VAR = #BFC798.(request).ConfigItem.Name;\n//var VAR_0 = #FFCFB5.(response).success.result[].title;","simpleCode":null,"language":"js","links":[]},"to":[{"color":"#BFC798","type":"request","field":"ConfigItem.Name","links":[]}],"links":[]},{"from":[{"color":"#C77E7E","type":"response","field":"success.result[]","links":[]}],"enhancement":{"enhanceId":null,"name":"","description":"","expertCode":"if( VAR_0.length > 0 ){\n  RESULT_VAR = VAR_0[0].manufacturer.title;\n}else{\n  RESULT_VAR = \"\";\n}","expertVar":"//var RESULT_VAR = #BFC798.(request).ConfigItem.CIXMLData.Vendor;\n//var VAR_0 = #C77E7E.(response).success.result[];","simpleCode":null,"language":"js","links":[]},"to":[{"color":"#BFC798","type":"request","field":"ConfigItem.CIXMLData.Vendor","links":[]}],"links":[]},{"from":[{"color":"#C77E7E","type":"response","field":"success.result[]","links":[]}],"enhancement":{"enhanceId":null,"name":"","description":"","expertCode":"if( VAR_0.length > 0 ){\n  RESULT_VAR = VAR_0[0].manufacturer.title;\n}else{\n  RESULT_VAR = \"\";\n}","expertVar":"//var RESULT_VAR = #9EC798.(request).ConfigItem.CIXMLData.Vendor;\n//var VAR_0 = #C77E7E.(response).success.result[];","simpleCode":null,"language":"js","links":[]},"to":[{"color":"#9EC798","type":"request","field":"ConfigItem.CIXMLData.Vendor","links":[]}],"links":[]},{"from":[{"color":"#FFCFB5","type":"response","field":"success.result[].title","links":[]},{"color":"#98BEC7","type":"response","field":"success.ConfigItem[]","links":[]}],"enhancement":{"enhanceId":null,"name":"","description":"","expertCode":"\nfor(var i = 0; i < VAR_0.length; i++){\n  if(VAR_0[i].Name == VAR_1){\n    RESULT_VAR = VAR_0[i].ConfigItemID;\n  }\n}","expertVar":"//var RESULT_VAR = #E6E6EA.(request).ConfigItemID;\n//var VAR_0 = #98BEC7.(response).success.ConfigItem[];\n//var VAR_1 = #FFCFB5.(response).success.result[].title;","simpleCode":null,"language":"js","links":[]},"to":[{"color":"#E6E6EA","type":"request","field":"ConfigItemID","links":[]}],"links":[]},{"from":[{"color":"#FFCFB5","type":"response","field":"success.result[].title","links":[]}],"enhancement":{"enhanceId":null,"name":"","description":"","expertCode":"RESULT_VAR = VAR_0;","expertVar":"//var RESULT_VAR = #E6E6EA.(request).ConfigItem.Name;\n//var VAR_0 = #FFCFB5.(response).success.result[].title;","simpleCode":null,"language":"js","links":[]},"to":[{"color":"#E6E6EA","type":"request","field":"ConfigItem.Name","links":[]}],"links":[]},{"from":[{"color":"#FFCFB5","type":"response","field":"success.result[].cmdb_status_title","links":[]}],"enhancement":{"enhanceId":null,"name":"","description":"","expertCode":"RESULT_VAR = \"Operational\";\n\nif(VAR_0 != \"in operation\"){\n  RESULT_VAR = \"Incident\";\n}","expertVar":"//var RESULT_VAR = #E6E6EA.(request).ConfigItem.InciState;\n//var VAR_0 = #FFCFB5.(response).success.result[].cmdb_status_title;","simpleCode":null,"language":"js","links":[]},"to":[{"color":"#E6E6EA","type":"request","field":"ConfigItem.InciState","links":[]}],"links":[]},{"from":[{"color":"#FFCFB5","type":"response","field":"success.result[].cmdb_status_title","links":[]}],"enhancement":{"enhanceId":null,"name":"","description":"","expertCode":"RESULT_VAR = \"Operational\";\n\nif(VAR_0 != \"in operation\"){\n  RESULT_VAR = \"Incident\";\n}","expertVar":"//var RESULT_VAR = #9EC798.(request).ConfigItem.InciState;\n//var VAR_0 = #FFCFB5.(response).success.result[].cmdb_status_title;","simpleCode":null,"language":"js","links":[]},"to":[{"color":"#9EC798","type":"request","field":"ConfigItem.InciState","links":[]}],"links":[]},{"from":[{"color":"#FFCFB5","type":"response","field":"success.result[].cmdb_status_title","links":[]}],"enhancement":{"enhanceId":null,"name":"","description":"","expertCode":"RESULT_VAR = \"Operational\";\n\nif(VAR_0 != \"in operation\"){\n  RESULT_VAR = \"Incident\";\n}","expertVar":"//var RESULT_VAR = #BFC798.(request).ConfigItem.InciState;\n//var VAR_0 = #FFCFB5.(response).success.result[].cmdb_status_title;","simpleCode":null,"language":"js","links":[]},"to":[{"color":"#BFC798","type":"request","field":"ConfigItem.InciState","links":[]}],"links":[]}],"links":[]}}
